{
  "device_info": {
    "manufacturer": "Xiaomi",
    "api": 30,
    "locale": "zh-CN"
  },
  "verified": false,
  "last_update": {
    "target_api": 26,
    "flags": "read_storage, write_storage",
    "version_code": 16400,
    "timestamp": 1664606382,
    "version_name": "1.6.4"
  },
  "package": "com.mukapp.genshintool",
  "recommendation": "@recommended",
  "behaviors": [
    "@abuse"
  ],
  "non_standard_files": [
    "AndroLua",
    "Download/MUKGenshinTool",
    "Pictures/MUKGenshinTool"
  ]
}